{"l/NB6Rf3+O4mGRjWuJi64A==":"bkg01-2000x1125.jpg","Wp/gYt90PllR7hCC0h1CqQ==":"sprava_logo-128x128.png","BoNMhug+LoyY4XlS1hwvrg==":"sprava_log1-128x128.jpg","CRwxl8gf2NOLDDtXq+P5pA==":"logo_simple-136x128.png","bCULcrjKg486WjEpQSs5bw==":"logo_circle-125x128.png","V6fH5iR8DdnK55NZI841Vw==":"sprava-log1-1-128x128.png","Z2gElOsEO0+z3jBoniNfag==":"logo_simple_white-147x128.png","qyLFRblE9yuqvlzFYDwyDQ==":"sprava5-2000x971.jpg","WomAjW1I4QyHz/Frm7K7/w==":"sprava4-2000x971.jpg","zQuqxXy85NuABLRkd+kWMw==":"unnamed-2000x1334.jpg","wbWUnoybywa39y/X3mOgHQ==":"11-2000x1333.jpg","VLR+b6HmroQuCtI4nP1WSg==":"12-2000x1339.jpg"}